hodgepodge/__init__.py
hodgepodge/archiving.py
hodgepodge/cli/__init__.py
hodgepodge/cli/__main__.py
hodgepodge/cli/command_groups/__init__.py
hodgepodge/cli/command_groups/commands.py
hodgepodge/cli/command_groups/file.py
hodgepodge/cli/command_groups/processes.py
hodgepodge/click.py
hodgepodge/commands.py
hodgepodge/compression.py
hodgepodge/constants.py
hodgepodge/error.py
hodgepodge/files.py
hodgepodge/hashing.py
hodgepodge/http.py
hodgepodge/logging.py
hodgepodge/math.py
hodgepodge/networking.py
hodgepodge/numbers.py
hodgepodge/pattern_matching.py
hodgepodge/platforms.py
hodgepodge/processes.py
hodgepodge/serialization.py
hodgepodge/stix.py
hodgepodge/time.py
hodgepodge/types.py
hodgepodge/users.py
hodgepodge/uuid.py
hodgepodge/ux.py
hodgepodge/web.py
hodgepodge-4.0.0.dist-info/entry_points.txt
hodgepodge-4.0.0.dist-info/LICENSE.md
hodgepodge-4.0.0.dist-info/WHEEL
hodgepodge-4.0.0.dist-info/METADATA
hodgepodge-4.0.0.dist-info/RECORD
