Metadata-Version: 2.1
Name: hodgepodge
Version: 4.0.0
Summary: 
Home-page: https://github.com/whitfieldsdad/hodgepodge
License: MIT
Author: Tyler Fisher
Author-email: tylerfisher@tylerfisher.ca
Requires-Python: >=3.6.0,<4
Classifier: License :: OSI Approved :: MIT License
Classifier: Programming Language :: Python :: 3
Classifier: Programming Language :: Python :: 3.10
Classifier: Programming Language :: Python :: 3.6
Classifier: Programming Language :: Python :: 3.7
Classifier: Programming Language :: Python :: 3.8
Classifier: Programming Language :: Python :: 3.9
Requires-Dist: arrow (>=1.0.3,<1.1.0)
Requires-Dist: click (>=7.0,<8.0)
Requires-Dist: psutil (>=5.8.0,<6.0.0)
Requires-Dist: python-dateutil (>=2.7.3,<2.8.0)
Requires-Dist: requests (>=2.22.0,<2.23.0)
Requires-Dist: setuptools (>=45.2.0,<45.3.0)
Requires-Dist: stix2 (>=3.0.1,<4.0.0)
Requires-Dist: taxii2-client (>=2.3.0,<3.0.0)
Requires-Dist: urllib3 (>=1.25.8,<1.26.0)
Project-URL: Repository, https://github.com/whitfieldsdad/hodgepodge
